pyloudnorm/__init__.py
pyloudnorm/iirfilter.py
pyloudnorm/meter.py
pyloudnorm/normalize.py
pyloudnorm/util.py
pyloudnorm-0.1.0.dist-info/LICENSE
pyloudnorm-0.1.0.dist-info/METADATA
pyloudnorm-0.1.0.dist-info/WHEEL
pyloudnorm-0.1.0.dist-info/top_level.txt
pyloudnorm-0.1.0.dist-info/RECORD
