Metadata-Version: 2.1
Name: pyloudnorm
Version: 0.1.0
Summary: Implementation of ITU-R BS.1770-4 loudness algorithm in Python
Home-page: https://github.com/csteinmetz1/pyloudnorm
Author: Christian Steinmetz
Author-email: cjstein@g.clemson.edu
License: UNKNOWN
Platform: UNKNOWN
Classifier: Programming Language :: Python :: 3
Classifier: Programming Language :: Python :: 2.7
Classifier: License :: OSI Approved :: MIT License
Classifier: Operating System :: OS Independent
